run_module/__init__.py
run_module/__main__.py
run_module-0.1.2.dist-info/WHEEL
run_module-0.1.2.dist-info/entry_points.txt
run_module-0.1.2.dist-info/METADATA
run_module-0.1.2.dist-info/RECORD
