Metadata-Version: 2.4
Name: run-module
Version: 0.1.2
Summary: A thin wrapper around runpy.run_module for use with uvx, pipx, etc.
Keywords: runpy,run_module,uvx,pipx,cli
Author: Mike Clark
Author-email: Mike Clark <mevanlc@gmail.com>
License-Expression: MIT
Classifier: Development Status :: 5 - Production/Stable
Classifier: Environment :: Console
Classifier: Intended Audience :: Developers
Classifier: License :: OSI Approved :: MIT License
Classifier: Programming Language :: Python :: 3
Classifier: Programming Language :: Python :: 3.9
Classifier: Programming Language :: Python :: 3.10
Classifier: Programming Language :: Python :: 3.11
Classifier: Programming Language :: Python :: 3.12
Classifier: Programming Language :: Python :: 3.13
Classifier: Programming Language :: Python :: 3.14
Classifier: Topic :: Software Development
Classifier: Topic :: Utilities
Requires-Python: >=3.9
Project-URL: Homepage, https://github.com/mevanlc/run-module
Project-URL: Repository, https://github.com/mevanlc/run-module
Project-URL: Issues, https://github.com/mevanlc/run-module/issues
